{
  "basics": {
    "name": "Hangbo Zhang",
    "label": "Student",
    "picture": "https://hangbozhang.github.io/images/head.jpg",
    "email": "hangbo@hawaii.edu",
    "phone": "",
    "website": "https://hangbo.github.io",
    "summary": "I am graduating with M.S. in Computer Science in the Department of Information and Computer Sciences at the University of Hawaii.",
    "location": {
      "address": "",
      "postalCode": "96706",
      "city": "Ewa Beach",
      "countryCode": "USA",
      "region": "Hawaii"
    },
    "profiles": [
      {
        "network": "github",
        "username": "hangbozhang",
        "url": "http://github.com/hangbozhang"
      },
      {
        "network": "linkedin",
        "username": "hangbo zhang",
        "url": "http://linkedin.com/in/hangbo-zhang-2b0ab37b/"
      }
    ]
  },
  "interests": [
    {
      "name": "software engineering",
      "keywords": [
        "Web application"

      ]
    },
    {
      "name": "cyber security",
      "keywords": [
        "NCL"
      ]
    },
    {
      "name": "database",
      "keywords": [
        "MySQL"
      ]
    }
  ],
  "skills": [
    {
      "name": "Languages and Frameworks",
      "level": "",
      "keywords": [
        "C",
        "C++",
        "Java",
        "Javascript",
        "HTML",
        "PHP",
        "Python",
        "C#"
      ]
    },
    {
      "name": "Toolsets/OS",
      "level": "",
      "keywords": [
        "Ubuntu",
        "Git/GitHub",
        "IntelliJ",
        "Visual Studio Code",
        "Meteor/React/Semantic UI",
        "MongoDB",
        "NoSQL",
        "MySQL",
        "Windows",
        "Unix",
        "Eclipse",
        "Unity",
        "Android Studio",
        "Blender"
      ]
    }
  ],
  "education": [
    {
      "institution": "University of Hawaii, Honolulu, HI",
      "area": "Computer Science (Graduating, Spring 2024)",
      "studyType": "M.S.",
      "startDate": "2022-08-22",
      "endDate": "2024-05-10",
      "gpa": "3.96",
      "courses": [
      ]
    },
    {
      "institution": "University of Hawaii, Honolulu, HI",
      "area": "Computer Science (Graduated, Spring 2022)",
      "studyType": "B.S.",
      "startDate": "2020-01-12",
      "endDate": "2022-05-13",
      "gpa": "3.92",
      "courses": [
      ]
    }
  ],
  "work": [
    {
      "company": "XFORCE, and Eccalon LLC",
      "position": "Summer Intern as Software Developer",
      "website": "",
      "startDate": "2023-06-01",
      "endDate": "2023-08-23",
      "summary": "Developed and published a web application for 25th ID CAB for their phase maintenance inspection. Enable them to track the maintenance scheduling and prediction.",
      "highlights": [
        "web application development",
        "database design",
        "product management",
        "communication with clients"
      ]
    },
    {
      "company": "University of Hawaii at Manoa",
      "position": "Teaching Assistant",
      "website": "https://www2.hawaii.edu/~hangbo/spring24/",
      "startDate": "2022-08-22",
      "endDate": "2024-05-10",
      "summary": "TA for ICS 111 (Java) and ICS 212 (C/C++)",
      "highlights": [
        "Teaching Labs",
        "Grading assignments",
        "Holding office hours"
      ]
    },
    {
      "company": "US Army",
      "position": "Combat Engineer Team Leader",
      "website": "",
      "startDate": "2015-03-31",
      "endDate": "2019-09-30",
      "summary": "Lead a team of 4 to accomplish any assigned missions",
      "highlights": [
        "team management and time management",
        "communication bridge between team members and higher up"
      ]
    },
    {
      "company": "University of North Dakota CSSA",
      "position": "Lead Web Developer",
      "website": "https://involvement.und.edu/organization/cssa",
      "startDate": "2012-12-01",
      "endDate": "2014-12-10",
      "summary": "control the CSSA website maintenance and updates",
      "highlights": [
        "Maintain, update, and oversee official CSSA student club website"
      ]
    }
  ],
  "volunteer": [
    {
      "organization": "",
      "website": "",
      "position": "Professional organization involvement",
      "startDate": "",
      "endDate": "",
      "summary": "",
      "highlights": [
        "Member, ACM Manoa, 2020-Present",
        "Participate in fall 2020 NCL competition"
      ]
    }
  ],
  "awards": [
    {
      "title": "Dean's list",
      "date": "2013-2014",
      "awarder": "University of North Dakota",
      "summary": "Dean's list for 2 semester with GPA over 3.5"
    },
    {
      "title": "Army Good Conduct Metal",
      "date": "2018",
      "awarder": "US Army 25th ID 65th Engineer Battalion",
      "summary": "Army Good Conduct Metal is awarded to a soldier who maintain high level of discipline"
    },
    {
      "title": "Army Achievement Metal",
      "date": "2019",
      "awarder": "US Army 25th ID 65th Engineer Battalion",
      "summary": "I was awarded AAM for the development of the standard of procedure for a new technology equipment and expert performance in the remote control weapon system."
    },
    {
      "title": "Dean's list",
      "date": "2020-present",
      "awarder": "University of Hawaii at Manoa",
      "summary": "Dean's list for 4 semester with GPAs over 3.8"
    }
  ],
  "references": [
    {
      "name": "Available upon request",
      "reference": ""
    }
  ]
}
